PayPayPy/__init__.py
PayPayPy/main.py
PayPayPy-1.0.3.dist-info/LICENSE
PayPayPy-1.0.3.dist-info/METADATA
PayPayPy-1.0.3.dist-info/WHEEL
PayPayPy-1.0.3.dist-info/top_level.txt
PayPayPy-1.0.3.dist-info/RECORD
