Metadata-Version: 2.1
Name: PayPayPy
Version: 1.0.3
Summary: PayPayのログインから情報の取得、リンクの受け取りや送金を行えます
Home-page: https://github.com/SpecialAgency-Chat/paypaypy
Author: 神瀬来未
Author-email: info@vxxx.cf
License: GPL-3.0
Keywords: paypay backend frontend api unofficial private
Platform: UNKNOWN
Classifier: License :: OSI Approved :: GNU General Public License v3 (GPLv3)
Classifier: Programming Language :: Python :: 3.9
License-File: LICENSE
Requires-Dist: requests
Requires-Dist: attrdict
Requires-Dist: datetime
Requires-Dist: uuid
